{"value":{"attendanceDate":"2026-05-17","records":[{"id":"live-clock-20260517-354","employeeId":"C2460","employeeName":"AKPO JACOB","businessUnit":"IDI-ORO","department":"PRODUCTION","jobTitle":"Not Assigned","location":"IDI-ORO","site":"Agege","shift":"Day","status":"Late","checkInTime":"08:43","checkOutTime":"15:08","scheduledStart":"08:00","scheduledEnd":"17:00","minutesLate":43,"overtimeHours":0,"biometricSource":"Biometric Device","supervisor":"IDI-ORO","punchCount":2},{"id":"live-clock-20260517-1027","employeeId":"C1096","employeeName":"DUROJAYE ADEDOYI","businessUnit":"IDI-ORO","department":"MAINTENANCE","jobTitle":"Not Assigned","location":"IDI-ORO","site":"Agege","shift":"Day","status":"Present","checkInTime":"06:50","checkOutTime":"15:14","scheduledStart":"08:00","scheduledEnd":"17:00","minutesLate":0,"overtimeHours":0,"biometricSource":"Biometric Device","supervisor":"IDI-ORO","punchCount":2},{"id":"live-clock-20260517-1137","employeeId":"L1986","employeeName":"EDET OKPOK ","businessUnit":"IDI-ORO","department":"SECURITY ","jobTitle":"Not Assigned","location":"IDI-ORO","site":"Idi-Oro 1","shift":"Day","status":"Present","checkInTime":"06:37","checkOutTime":"15:34","scheduledStart":"08:00","scheduledEnd":"17:00","minutesLate":0,"overtimeHours":0,"biometricSource":"Biometric Device","supervisor":"IDI-ORO","punchCount":2},{"id":"live-clock-20260517-1012","employeeId":"C0695","employeeName":"JULIUS AWOYEMI ","businessUnit":"AGEGE","department":"PRODUCTION","jobTitle":"Not Assigned","location":"AGEGE","site":"Agege","shift":"Day","status":"Present","checkInTime":"06:37","checkOutTime":null,"scheduledStart":"08:00","scheduledEnd":"17:00","minutesLate":0,"overtimeHours":0,"biometricSource":"Biometric Device","supervisor":"AGEGE","punchCount":1},{"id":"live-clock-20260517-1066","employeeId":"C1705","employeeName":"MATHEW ROTIMI ","businessUnit":"Not Assigned","department":"Not Assigned","jobTitle":"Not Assigned","location":"Not Assigned","site":"Agege","shift":"Day","status":"Late","checkInTime":"10:06","checkOutTime":null,"scheduledStart":"08:00","scheduledEnd":"17:00","minutesLate":126,"overtimeHours":0,"biometricSource":"Biometric Device","supervisor":"Not Assigned","punchCount":1},{"id":"live-clock-20260517-17","employeeId":"P0076","employeeName":"NATHANIEL OBUZOR","businessUnit":"IDI-ORO","department":"QUALITY CONTROL","jobTitle":"Not Assigned","location":"IDI-ORO","site":"Idi-Oro 1","shift":"Night","status":"Present","checkInTime":"05:03","checkOutTime":"18:06","scheduledStart":"18:00","scheduledEnd":"06:00","minutesLate":0,"overtimeHours":4.1,"biometricSource":"Biometric Device","supervisor":"IDI-ORO","punchCount":2},{"id":"live-clock-20260517-58","employeeId":"P0316","employeeName":"NDUKWE CHUKWUMA","businessUnit":"AGEGE","department":"MAINTENANCE","jobTitle":"Not Assigned","location":"AGEGE","site":"Agege","shift":"Day","status":"Late","checkInTime":"09:37","checkOutTime":"14:33","scheduledStart":"08:00","scheduledEnd":"17:00","minutesLate":97,"overtimeHours":0,"biometricSource":"Biometric Device","supervisor":"AGEGE","punchCount":2},{"id":"live-clock-20260517-1138","employeeId":"C1989","employeeName":"OLAWALE SADIQ ","businessUnit":"AGEGE","department":"PRODUCTION","jobTitle":"Not Assigned","location":"AGEGE","site":"Agege","shift":"Day","status":"Present","checkInTime":"08:17","checkOutTime":"16:40","scheduledStart":"08:00","scheduledEnd":"17:00","minutesLate":17,"overtimeHours":0,"biometricSource":"Biometric Device","supervisor":"AGEGE","punchCount":2},{"id":"live-clock-20260517-467","employeeId":"C2523","employeeName":"OMOGBOLAHAN RASA","businessUnit":"AGEGE","department":"PRODUCTION","jobTitle":"Not Assigned","location":"AGEGE","site":"Agege","shift":"Night","status":"Late","checkInTime":"18:30","checkOutTime":null,"scheduledStart":"18:00","scheduledEnd":"06:00","minutesLate":30,"overtimeHours":0,"biometricSource":"Biometric Device","supervisor":"AGEGE","punchCount":1},{"id":"live-clock-20260517-1189","employeeId":"C2138","employeeName":"STANLEY AIGBEVBO","businessUnit":"AGEGE","department":"PROJECT","jobTitle":"Not Assigned","location":"AGEGE","site":"Agege","shift":"Day","status":"Present","checkInTime":"07:34","checkOutTime":"15:14","scheduledStart":"08:00","scheduledEnd":"17:00","minutesLate":0,"overtimeHours":0,"biometricSource":"Biometric Device","supervisor":"AGEGE","punchCount":3},{"id":"live-clock-20260517-593","employeeId":"P0436","employeeName":"SUNDAY OKEWU ","businessUnit":"IDI-ORO","department":"MAINTENANCE","jobTitle":"Not Assigned","location":"IDI-ORO","site":"Idi-Oro 1","shift":"Day","status":"Late","checkInTime":"12:45","checkOutTime":"14:39","scheduledStart":"08:00","scheduledEnd":"17:00","minutesLate":285,"overtimeHours":0,"biometricSource":"Biometric Device","supervisor":"IDI-ORO","punchCount":2},{"id":"live-clock-20260517-319","employeeId":"C2492","employeeName":"TIMOTHY OGWUA","businessUnit":"IDI-ORO","department":"MAINTENANCE","jobTitle":"Not Assigned","location":"IDI-ORO","site":"Idi-Oro 1","shift":"Day","status":"Late","checkInTime":"08:54","checkOutTime":"18:28","scheduledStart":"08:00","scheduledEnd":"17:00","minutesLate":54,"overtimeHours":0.6,"biometricSource":"Biometric Device","supervisor":"IDI-ORO","punchCount":2}]},"expiresAt":1781690867286,"staleUntil":1781734057286}